payments_config
