Metadata-Version: 1.0
Name: payments-config
Version: 0.0.13
Summary: Payments Configuration
Home-page: https://github.com/andymckay/payments-config
Author: Andy McKay
Author-email: andym@mozilla.com
License: BSD
Platform: UNKNOWN
